ucapi_framework/__init__.py
ucapi_framework/config.py
ucapi_framework/device.py
ucapi_framework/discovery.py
ucapi_framework/driver.py
ucapi_framework/entity.py
ucapi_framework/helpers.py
ucapi_framework/migration.py
ucapi_framework/setup.py
ucapi_framework-1.8.3.dist-info/METADATA
ucapi_framework-1.8.3.dist-info/WHEEL
ucapi_framework-1.8.3.dist-info/top_level.txt
ucapi_framework-1.8.3.dist-info/RECORD
