Metadata-Version: 2.4
Name: ucapi-framework
Version: 1.8.3
Summary: ucapi framework that provides core functionality for building integrations.
Requires-Python: >=3.11
Requires-Dist: pyee>=9.0.0
Requires-Dist: ucapi>=0.5.2
Requires-Dist: aiohttp>=3.9.0
